[{"domain":".instagram.com","expires":1761539420.021091,"httpOnly":true,"name":"ig_did","path":"\/","priority":"Medium","sameParty":false,"sameSite":"None","secure":true,"session":false,"size":42,"sourcePort":443,"sourceScheme":"Secure","value":"3E39B087-C17D-45C4-887A-F9C18E29B2BF"},{"domain":".instagram.com","expires":1764563421.587091,"httpOnly":true,"name":"datr","path":"\/","priority":"Medium","sameParty":false,"sameSite":"None","secure":true,"session":false,"size":28,"sourcePort":443,"sourceScheme":"Secure","value":"3cEdZ0Jg0M3Q1rQOS4OKDoZ4"},{"domain":".instagram.com","expires":1730608411,"httpOnly":false,"name":"wd","path":"\/","priority":"Medium","sameParty":false,"sameSite":"Lax","secure":true,"session":false,"size":10,"sourcePort":443,"sourceScheme":"Secure","value":"1024x599"},{"domain":".instagram.com","expires":1764563435,"httpOnly":false,"name":"mid","path":"\/","priority":"Medium","sameParty":false,"secure":true,"session":false,"size":31,"sourcePort":443,"sourceScheme":"Secure","value":"Zx3B3QALAAGG9o7P4l1SJgNnc77O"},{"domain":".instagram.com","expires":1761539518.5979781,"httpOnly":false,"name":"ig_nrcb","path":"\/","priority":"Medium","sameParty":false,"secure":true,"session":false,"size":8,"sourcePort":443,"sourceScheme":"Secure","value":"1"},{"domain":".2fa-auth.com","expires":1764563531.743938,"httpOnly":false,"name":"_ga","path":"\/","priority":"Medium","sameParty":false,"secure":false,"session":false,"size":29,"sourcePort":443,"sourceScheme":"Secure","value":"GA1.1.956818018.1730003532"},{"domain":".2fa-auth.com","expires":1764563548.2619381,"httpOnly":false,"name":"_ga_C20N2YY0HD","path":"\/","priority":"Medium","sameParty":false,"secure":false,"session":false,"size":51,"sourcePort":443,"sourceScheme":"Secure","value":"GS1.1.1730003531.1.1.1730003548.0.0.0"},{"domain":".instagram.com","expires":1761453215.41101,"httpOnly":false,"name":"csrftoken","path":"\/","priority":"Medium","sameParty":false,"secure":true,"session":false,"size":41,"sourcePort":443,"sourceScheme":"Secure","value":"qll2yzcmFbJl2ezu6YiNH4C2i4u5kOti"},{"domain":".instagram.com","expires":1761539555.1429379,"httpOnly":true,"name":"sessionid","path":"\/","priority":"Medium","sameParty":false,"secure":true,"session":false,"size":87,"sourcePort":443,"sourceScheme":"Secure","value":"70126443187%3APSJGE1yxkP66Q3%3A10%3AAYcoY6blPwuo_tbgxWW8jIwzgpl3KuaQ-0C9pZHQww"},{"domain":".instagram.com","expires":1737779615.41101,"httpOnly":false,"name":"ds_user_id","path":"\/","priority":"Medium","sameParty":false,"secure":true,"session":false,"size":21,"sourcePort":443,"sourceScheme":"Secure","value":"70126443187"},{"domain":".instagram.com","expires":1764563569,"httpOnly":false,"name":"ig_lang","path":"\/","priority":"Medium","sameParty":false,"secure":false,"session":false,"size":9,"sourcePort":443,"sourceScheme":"Secure","value":"ru"},{"domain":".instagram.com","expires":1764563572.2689381,"httpOnly":true,"name":"ps_l","path":"\/","priority":"Medium","sameParty":false,"sameSite":"Lax","secure":true,"session":false,"size":5,"sourcePort":443,"sourceScheme":"Secure","value":"1"},{"domain":".instagram.com","expires":1764563572.2689381,"httpOnly":true,"name":"ps_n","path":"\/","priority":"Medium","sameParty":false,"sameSite":"None","secure":true,"session":false,"size":5,"sourcePort":443,"sourceScheme":"Secure","value":"1"},{"domain":".instagram.com","expires":-1,"httpOnly":true,"name":"rur","path":"\/","priority":"Medium","sameParty":false,"sameSite":"Lax","secure":true,"session":true,"size":110,"sourcePort":443,"sourceScheme":"Secure","value":"\"CLN\\05470126443187\\0541761539615:01f7ad1be498a0c2c72c6a3d6139408fbee61cec792b13449360dce3a7cd5aedc8aca7d2\""}]